uaf_mcp/__init__.py
uaf_mcp/api.py
uaf_mcp/server.py
uaf_mcp/transfer.py
uaf_mcp-0.1.0.dist-info/METADATA
uaf_mcp-0.1.0.dist-info/WHEEL
uaf_mcp-0.1.0.dist-info/top_level.txt
uaf_mcp-0.1.0.dist-info/RECORD
