Metadata-Version: 2.4
Name: uaf-mcp
Version: 0.1.0
Summary: a mcp server for uaf modeling
License-Expression: MIT
Requires-Python: >=3.13
Requires-Dist: fastmcp>=2.2.7
Requires-Dist: requests>=2.32.3
